RNAseqpipe/NOISeq.py
RNAseqpipe/RNAseqpip.py
RNAseqpipe/VERSION
RNAseqpipe/__init__.py
RNAseqpipe/_version.py
RNAseqpipe/conv_clipping.sh
RNAseqpipe/cptDE.py
RNAseqpipe/cufflinks.py
RNAseqpipe/expression_filter.py
RNAseqpipe/func.py
RNAseqpipe/get_gene_length.py
RNAseqpipe/get_geneids.py
RNAseqpipe/gtf_cuff_table.py
RNAseqpipe/hisat.py
RNAseqpipe/htseq.py
RNAseqpipe/progsuit.py
RNAseqpipe/run_RNAseqpipe.py
RNAseqpipe/seq2exp.py
RNAseqpipe/stringtie.py
RNAseqpipe/verse.py
RNAseqpipe/confs/QC.conf
RNAseqpipe/confs/RNApip_lnc.conf
RNAseqpipe/confs/base.back
RNAseqpipe/confs/base.conf
RNAseqpipe/confs/base.template
RNAseqpipe/confs/dUTP.conf
RNAseqpipe/confs/fr_firststrand.conf
RNAseqpipe/confs/fr_secondstrand.conf
RNAseqpipe/confs/gc.conf
RNAseqpipe/confs/gc_no_gff.conf
RNAseqpipe/confs/hisat_cuff_verse.conf
RNAseqpipe/confs/hisat_htseq_count.conf
RNAseqpipe/confs/hisat_stringtie_verse.conf
RNAseqpipe/confs/hisat_verse_count.conf
RNAseqpipe/confs/hs38.conf
RNAseqpipe/confs/mRNA.conf
RNAseqpipe/confs/mm38.conf
RNAseqpipe/confs/test_gc.conf
RNAseqpipe/confs/test_gc_no_gff.conf
RNAseqpipe/confs/unstrand.conf
RNAseqpipe/confs/zf.conf
RNAseqpipe/confs/zf11.conf
RNAseqpipe/expression/__init__.py
RNAseqpipe/expression/count_merge.py
RNAseqpipe/expression/normalize.R
RNAseqpipe/expression/normalize.py
RNAseqpipe/expression/salmon_quantify.py
RNAseqpipe/expression/salmon_quantify.sh
RNAseqpipe/funcAnnot/__init__.py
RNAseqpipe/funcAnnot/annot_from_db.py
RNAseqpipe/funcAnnot/find_genes_in_genome.py
RNAseqpipe/funcAnnot/subset_fasta.py
RNAseqpipe/funcAnnot/b2gprog/GOannot.py
RNAseqpipe/funcAnnot/b2gprog/__init__.py
RNAseqpipe/funcAnnot/b2gprog/format_godb.R
RNAseqpipe/funcAnnot/b2gprog/gostat_goplot_RamiGO_in.R
RNAseqpipe/funcAnnot/b2gprog/gostat_goplot_RamiGO_out.R
RNAseqpipe/funcAnnot/b2gprog/gostats.R
RNAseqpipe/funcAnnot/b2gprog/tmp.R
RNAseqpipe/funcAnnot/blast2go/blast2go.sh
RNAseqpipe/funcAnnot/go/enrich_bubble.R
RNAseqpipe/funcAnnot/go/goplot.R
RNAseqpipe-0.0.6.2.dist-info/LICENSE
RNAseqpipe-0.0.6.2.dist-info/METADATA
RNAseqpipe-0.0.6.2.dist-info/WHEEL
RNAseqpipe-0.0.6.2.dist-info/top_level.txt
RNAseqpipe-0.0.6.2.dist-info/RECORD
