Metadata-Version: 2.1
Name: RNAseqpipe
Version: 0.0.6.2
Summary: Analysis pipeline for RNA-seq data
Home-page: https://github.com/yduanBioinfo/RNAseqpipe
Author: You Duan
Author-email: duanyou@outlook.com
License: UNKNOWN
Platform: UNKNOWN
Classifier: Programming Language :: Python :: 3
Classifier: License :: OSI Approved :: GNU General Public License v3 (GPLv3)
Classifier: Operating System :: OS Independent
Requires-Python: >=3.6
License-File: LICENSE
Requires-Dist: dypylib (>=0.0.3)
Requires-Dist: pyper
